dash_chart_editor/DashChartEditor.py
dash_chart_editor/__init__.py
dash_chart_editor/_imports_.py
dash_chart_editor/dash_chart_editor.min.js
dash_chart_editor/dash_chart_editor.min.js.map
dash_chart_editor/metadata.json
dash_chart_editor/package-info.json
dash_chart_editor/utils.py
dash_chart_editor-0.0.1a5.dist-info/LICENSE
dash_chart_editor-0.0.1a5.dist-info/METADATA
dash_chart_editor-0.0.1a5.dist-info/WHEEL
dash_chart_editor-0.0.1a5.dist-info/top_level.txt
dash_chart_editor-0.0.1a5.dist-info/RECORD
