Metadata-Version: 2.1
Name: dash-chart-editor
Version: 0.0.1a5
Summary: Dash wrapper for Plotly's react-chart-editor
Home-page: https://github.com/BSd3v/dash-chart-editor
Author: Bryan Schroeder <bryan.ri.schroeder@gmail.com>
License: MIT
Project-URL: Github, https://github.com/BSd3v/dash-chart-editor
Platform: UNKNOWN
Classifier: Framework :: Dash
License-File: LICENSE
